README.md
setup.py
K8sSilverStreamingApplication.egg-info/PKG-INFO
K8sSilverStreamingApplication.egg-info/SOURCES.txt
K8sSilverStreamingApplication.egg-info/dependency_links.txt
K8sSilverStreamingApplication.egg-info/top_level.txt
com/phida/main/Operations.py
com/phida/main/SilverMerge.py
com/phida/main/__init__.py
com/phida/main/config.py
com/phida/main/logging.py
com/phida/main/sparksession.py
com/phida/main/utils.py
com/phida/tests/OperationsTest.py
com/phida/tests/__init__.py
com/phida/tests/main_test.py
com/phida/tests/utils_test.py