Metadata-Version: 2.1
Name: K8sSilverStreamingApplication
Version: 1.2
Summary: For Demo
Home-page: UNKNOWN
Author: 
Author-email: 
License: UNKNOWN
Platform: UNKNOWN
